[
  {
    "build_number": 103,
    "dt_current_timestamp": 1772135281865738,
    "id": 2075,
    "manufacturer": "Motorola",
    "model": "Redmi Note 8",
    "platform": "iOS 14",
    "serial_number": "98d6a3f67c6d",
    "uid": "235a0f50-4f04-479f-a924-5c6a8cab2312",
    "user_id": 9365,
    "version": 316
  },
  {
    "build_number": 162,
    "dt_current_timestamp": 1772135281865757,
    "id": 2874,
    "manufacturer": "Samsung",
    "model": "Pocophone F1",
    "platform": "Android 11",
    "serial_number": "40f9d3ea3ae3",
    "uid": "43315f1b-424b-49c0-b5b9-ff32666fdda7",
    "user_id": 7011,
    "version": 451
  },
  {
    "build_number": 248,
    "dt_current_timestamp": 1772135281865767,
    "id": 9200,
    "manufacturer": "Huawei",
    "model": "Pocophone F1",
    "platform": "Windows 8.1",
    "serial_number": "ece00eb8aa6d",
    "uid": "96b70082-4961-4396-b435-4c22830db6e2",
    "user_id": 7027,
    "version": 19
  },
  {
    "build_number": 241,
    "dt_current_timestamp": 1772135281865775,
    "id": 1799,
    "manufacturer": "Xiaomi",
    "model": "Redmi Note 8",
    "platform": "Android 11",
    "serial_number": "81559dde2553",
    "uid": "4f64ac96-3204-480c-b98f-3e3c4cb9d906",
    "user_id": 2742,
    "version": 420
  },
  {
    "build_number": 345,
    "dt_current_timestamp": 1772135281865784,
    "id": 8468,
    "manufacturer": "Apple",
    "model": "Pocophone F1",
    "platform": "Android 11",
    "serial_number": "1e68004319f8",
    "uid": "b0591a34-11fa-43b3-a881-ee60c32331a2",
    "user_id": 2530,
    "version": 442
  },
  {
    "build_number": 350,
    "dt_current_timestamp": 1772135281865793,
    "id": 7601,
    "manufacturer": "Huawei",
    "model": "Pocophone F1",
    "platform": "Android 11",
    "serial_number": "065d6adfc1a3",
    "uid": "a222298f-25cb-4e62-8c06-e227ac1d366e",
    "user_id": 2329,
    "version": 318
  },
  {
    "build_number": 103,
    "dt_current_timestamp": 1772135281865801,
    "id": 8761,
    "manufacturer": "Xiaomi",
    "model": "Pocophone F1",
    "platform": "Windows 8.1",
    "serial_number": "4da6c118668b",
    "uid": "e8dff1ef-373f-4d82-825e-4dd18092ab71",
    "user_id": 4184,
    "version": 438
  },
  {
    "build_number": 427,
    "dt_current_timestamp": 1772135281865810,
    "id": 6237,
    "manufacturer": "Samsung",
    "model": "iPhone 12",
    "platform": "Android 10",
    "serial_number": "80f2ce30b97f",
    "uid": "3f115f76-0a5e-423a-9ca0-154d21f9b466",
    "user_id": 7930,
    "version": 122
  },
  {
    "build_number": 260,
    "dt_current_timestamp": 1772135281865829,
    "id": 1847,
    "manufacturer": "Samsung",
    "model": "iPhone 12",
    "platform": "Android 10",
    "serial_number": "bb171df5e3ea",
    "uid": "e9ac3b82-4ec8-4ea1-bd4a-05e655419f3b",
    "user_id": 6460,
    "version": 233
  },
  {
    "build_number": 300,
    "dt_current_timestamp": 1772135281865844,
    "id": 8477,
    "manufacturer": "Apple",
    "model": "Pocophone F1",
    "platform": "Windows 8.1",
    "serial_number": "70aac24f55fb",
    "uid": "7df80f80-6ad5-455d-a0ad-042ae9103789",
    "user_id": 6544,
    "version": 17
  },
  {
    "build_number": 445,
    "dt_current_timestamp": 1772135281865852,
    "id": 7930,
    "manufacturer": "Apple",
    "model": "Redmi Note 8",
    "platform": "Android 10",
    "serial_number": "e84d4d7d8c24",
    "uid": "9668761e-65d8-4b3b-8fea-abce6e323ba3",
    "user_id": 4871,
    "version": 246
  },
  {
    "build_number": 221,
    "dt_current_timestamp": 1772135281865861,
    "id": 6450,
    "manufacturer": "Xiaomi",
    "model": "Galaxy S9",
    "platform": "Android 11",
    "serial_number": "31ec6afec715",
    "uid": "3f450c00-6865-4a9c-b6bb-f0ef9fb268e1",
    "user_id": 2465,
    "version": 165
  },
  {
    "build_number": 344,
    "dt_current_timestamp": 1772135281865869,
    "id": 9344,
    "manufacturer": "Xiaomi",
    "model": "iPhone 12",
    "platform": "Windows 8.1",
    "serial_number": "9bd234df2c44",
    "uid": "2f9752e4-50a7-460a-b78c-4d08ab73f788",
    "user_id": 7091,
    "version": 499
  },
  {
    "build_number": 122,
    "dt_current_timestamp": 1772135281865880,
    "id": 8314,
    "manufacturer": "Motorola",
    "model": "iPhone 12",
    "platform": "Windows 8.1",
    "serial_number": "5e1b31f4977a",
    "uid": "f431c433-afc7-47ac-8a81-5836aa27c9e9",
    "user_id": 5093,
    "version": 328
  },
  {
    "build_number": 164,
    "dt_current_timestamp": 1772135281865889,
    "id": 9052,
    "manufacturer": "Huawei",
    "model": "Galaxy S9",
    "platform": "Windows 10",
    "serial_number": "9be561c3291f",
    "uid": "6bdcd151-2e2e-44e3-935e-35813fd5e68c",
    "user_id": 5958,
    "version": 429
  },
  {
    "build_number": 434,
    "dt_current_timestamp": 1772135281865897,
    "id": 9705,
    "manufacturer": "Huawei",
    "model": "Moto G9",
    "platform": "Windows 8.1",
    "serial_number": "76c4e8991284",
    "uid": "cb51e9d0-e1dc-4085-9ce9-b32fabf8b254",
    "user_id": 5441,
    "version": 425
  },
  {
    "build_number": 187,
    "dt_current_timestamp": 1772135281865906,
    "id": 1821,
    "manufacturer": "Huawei",
    "model": "Moto G9",
    "platform": "iOS 14",
    "serial_number": "2c7a0efe16a9",
    "uid": "6077fd0d-5372-463c-a54a-1effe71f719a",
    "user_id": 5290,
    "version": 26
  },
  {
    "build_number": 368,
    "dt_current_timestamp": 1772135281865914,
    "id": 6396,
    "manufacturer": "Samsung",
    "model": "Pocophone F1",
    "platform": "Windows 8.1",
    "serial_number": "8271ffc673fb",
    "uid": "6a300d77-e66f-4300-8d8d-c8eae0eafaf0",
    "user_id": 8329,
    "version": 385
  },
  {
    "build_number": 487,
    "dt_current_timestamp": 1772135281865922,
    "id": 2625,
    "manufacturer": "Samsung",
    "model": "Redmi Note 8",
    "platform": "Android 10",
    "serial_number": "e16d8e6e5a96",
    "uid": "14f207bd-0e0d-4b1a-ba9e-d7b8e2c77399",
    "user_id": 1578,
    "version": 418
  },
  {
    "build_number": 146,
    "dt_current_timestamp": 1772135281865930,
    "id": 8563,
    "manufacturer": "Xiaomi",
    "model": "Galaxy S9",
    "platform": "iOS 14",
    "serial_number": "c380b71a7294",
    "uid": "0b1838d2-db8c-45fe-96ad-13c4482ee2ac",
    "user_id": 2256,
    "version": 142
  },
  {
    "build_number": 455,
    "dt_current_timestamp": 1772135281865939,
    "id": 3321,
    "manufacturer": "Xiaomi",
    "model": "Pocophone F1",
    "platform": "iOS 14",
    "serial_number": "1aed0d9644cd",
    "uid": "3a0a9b05-8c83-4ac5-a0bc-b26dd58e9eaf",
    "user_id": 2619,
    "version": 54
  },
  {
    "build_number": 398,
    "dt_current_timestamp": 1772135281865954,
    "id": 8740,
    "manufacturer": "Xiaomi",
    "model": "Pocophone F1",
    "platform": "Windows 10",
    "serial_number": "2ddd64f89d1f",
    "uid": "ed01f6eb-a1b3-446e-ab39-126ee3a9a5cc",
    "user_id": 4398,
    "version": 202
  },
  {
    "build_number": 497,
    "dt_current_timestamp": 1772135281865977,
    "id": 2065,
    "manufacturer": "Samsung",
    "model": "Galaxy S9",
    "platform": "Windows 10",
    "serial_number": "02505f11b72b",
    "uid": "b2881650-f859-41dc-99e1-c1336400c486",
    "user_id": 7674,
    "version": 460
  },
  {
    "build_number": 435,
    "dt_current_timestamp": 1772135281865985,
    "id": 5943,
    "manufacturer": "Motorola",
    "model": "Redmi Note 8",
    "platform": "Android 10",
    "serial_number": "8adc137d86f8",
    "uid": "6ae01229-8d6b-4e98-b0fb-7c17e7865a0e",
    "user_id": 6669,
    "version": 39
  },
  {
    "build_number": 200,
    "dt_current_timestamp": 1772135281865993,
    "id": 8272,
    "manufacturer": "Samsung",
    "model": "Moto G9",
    "platform": "Android 11",
    "serial_number": "2ea0a111ff7e",
    "uid": "35a98842-ba4d-44db-9d10-27586f3f9843",
    "user_id": 7610,
    "version": 300
  },
  {
    "build_number": 430,
    "dt_current_timestamp": 1772135281866013,
    "id": 9862,
    "manufacturer": "Xiaomi",
    "model": "Redmi Note 8",
    "platform": "Windows 10",
    "serial_number": "c95f442ab001",
    "uid": "2a907615-5820-4a00-ac2a-b2ba5c375825",
    "user_id": 6674,
    "version": 427
  },
  {
    "build_number": 261,
    "dt_current_timestamp": 1772135281866026,
    "id": 9700,
    "manufacturer": "Xiaomi",
    "model": "Moto G9",
    "platform": "Android 10",
    "serial_number": "e98a6b40ceea",
    "uid": "ab1ba95c-d8f1-44da-b955-34ef18547d33",
    "user_id": 9421,
    "version": 322
  },
  {
    "build_number": 442,
    "dt_current_timestamp": 1772135281866035,
    "id": 3490,
    "manufacturer": "Huawei",
    "model": "Moto G9",
    "platform": "iOS 14",
    "serial_number": "225e3818cd30",
    "uid": "cc06edea-1075-481b-8d99-7723f888ad77",
    "user_id": 7442,
    "version": 113
  },
  {
    "build_number": 434,
    "dt_current_timestamp": 1772135281866043,
    "id": 5842,
    "manufacturer": "Motorola",
    "model": "iPhone 12",
    "platform": "iOS 14",
    "serial_number": "22c2984d8c7a",
    "uid": "f5dc2982-dbc1-45cb-9b29-d9b47e2de8b9",
    "user_id": 4349,
    "version": 67
  },
  {
    "build_number": 327,
    "dt_current_timestamp": 1772135281866052,
    "id": 8369,
    "manufacturer": "Apple",
    "model": "Galaxy S9",
    "platform": "Windows 8.1",
    "serial_number": "384ad6479fff",
    "uid": "67a761b9-3586-43b7-ad52-4b5370006554",
    "user_id": 3642,
    "version": 304
  },
  {
    "build_number": 363,
    "dt_current_timestamp": 1772135281866059,
    "id": 6497,
    "manufacturer": "Xiaomi",
    "model": "Pocophone F1",
    "platform": "iOS 14",
    "serial_number": "c16268fc4efe",
    "uid": "c9abe5e5-4efb-49b8-b43d-58ad229fca13",
    "user_id": 7662,
    "version": 42
  },
  {
    "build_number": 335,
    "dt_current_timestamp": 1772135281866067,
    "id": 4592,
    "manufacturer": "Samsung",
    "model": "Redmi Note 8",
    "platform": "Android 10",
    "serial_number": "a195eff815ab",
    "uid": "3a5de5b4-97ba-427f-973e-2338f6132067",
    "user_id": 5117,
    "version": 381
  },
  {
    "build_number": 196,
    "dt_current_timestamp": 1772135281866075,
    "id": 7305,
    "manufacturer": "Samsung",
    "model": "Moto G9",
    "platform": "Android 11",
    "serial_number": "c478f2f61b8b",
    "uid": "c8bd2325-00bd-42d5-9da8-0395adc24b77",
    "user_id": 2074,
    "version": 481
  },
  {
    "build_number": 439,
    "dt_current_timestamp": 1772135281866083,
    "id": 2404,
    "manufacturer": "Huawei",
    "model": "Moto G9",
    "platform": "Android 10",
    "serial_number": "486e44ffc0b5",
    "uid": "7cd6af99-6fe5-4c83-9a90-3e4beb1fc821",
    "user_id": 8652,
    "version": 305
  },
  {
    "build_number": 410,
    "dt_current_timestamp": 1772135281866102,
    "id": 3542,
    "manufacturer": "Motorola",
    "model": "Galaxy S9",
    "platform": "Android 11",
    "serial_number": "f30756ffb27c",
    "uid": "c0e59ffd-5cb7-4662-acb3-d025850a872a",
    "user_id": 9790,
    "version": 206
  },
  {
    "build_number": 224,
    "dt_current_timestamp": 1772135281866110,
    "id": 6863,
    "manufacturer": "Motorola",
    "model": "iPhone 12",
    "platform": "iOS 14",
    "serial_number": "85e1e75e90c1",
    "uid": "38919d04-dcc8-4b48-bc9f-3f93d778f9e9",
    "user_id": 1334,
    "version": 230
  },
  {
    "build_number": 171,
    "dt_current_timestamp": 1772135281866119,
    "id": 3447,
    "manufacturer": "Huawei",
    "model": "Galaxy S9",
    "platform": "Android 10",
    "serial_number": "cdfdef9926a8",
    "uid": "e1561e42-2c45-4591-8534-6fff94e9d1fe",
    "user_id": 2749,
    "version": 330
  },
  {
    "build_number": 348,
    "dt_current_timestamp": 1772135281866127,
    "id": 7982,
    "manufacturer": "Samsung",
    "model": "Pocophone F1",
    "platform": "Windows 10",
    "serial_number": "86ef5954cb11",
    "uid": "9f707946-e57c-44f9-b898-7f4395c24409",
    "user_id": 5819,
    "version": 380
  },
  {
    "build_number": 228,
    "dt_current_timestamp": 1772135281866135,
    "id": 5023,
    "manufacturer": "Xiaomi",
    "model": "Redmi Note 8",
    "platform": "Android 11",
    "serial_number": "e63434aca353",
    "uid": "d4317559-c012-4a83-bbd2-29d83f44775d",
    "user_id": 7123,
    "version": 238
  },
  {
    "build_number": 396,
    "dt_current_timestamp": 1772135281866144,
    "id": 1183,
    "manufacturer": "Huawei",
    "model": "iPhone 12",
    "platform": "Windows 8.1",
    "serial_number": "b5c87f25d67a",
    "uid": "45020615-6154-43d7-8c42-7066a89536bc",
    "user_id": 2216,
    "version": 67
  },
  {
    "build_number": 114,
    "dt_current_timestamp": 1772135281866152,
    "id": 9642,
    "manufacturer": "Huawei",
    "model": "Pocophone F1",
    "platform": "Windows 8.1",
    "serial_number": "9da6fd9d70a8",
    "uid": "50955024-9266-4217-aeb1-29bcb291994b",
    "user_id": 5998,
    "version": 117
  },
  {
    "build_number": 180,
    "dt_current_timestamp": 1772135281866159,
    "id": 8537,
    "manufacturer": "Motorola",
    "model": "Moto G9",
    "platform": "iOS 14",
    "serial_number": "06e561b737d0",
    "uid": "dbb14be6-27b6-497a-92db-c2633bf2f6be",
    "user_id": 3521,
    "version": 381
  },
  {
    "build_number": 133,
    "dt_current_timestamp": 1772135281866168,
    "id": 3511,
    "manufacturer": "Samsung",
    "model": "iPhone 12",
    "platform": "Windows 10",
    "serial_number": "ff61367e18bc",
    "uid": "053ae0c2-2829-4c02-8425-57c09058b002",
    "user_id": 4015,
    "version": 129
  },
  {
    "build_number": 124,
    "dt_current_timestamp": 1772135281866175,
    "id": 9054,
    "manufacturer": "Apple",
    "model": "Galaxy S9",
    "platform": "Android 10",
    "serial_number": "7f7e102d771d",
    "uid": "043c9c2e-4840-481c-b902-3ad580bb3538",
    "user_id": 6810,
    "version": 312
  },
  {
    "build_number": 232,
    "dt_current_timestamp": 1772135281866184,
    "id": 9821,
    "manufacturer": "Motorola",
    "model": "Pocophone F1",
    "platform": "Windows 10",
    "serial_number": "5f45b09c238e",
    "uid": "2c5082dc-6771-4de8-972b-62ad24892d5e",
    "user_id": 4446,
    "version": 333
  },
  {
    "build_number": 468,
    "dt_current_timestamp": 1772135281866191,
    "id": 6941,
    "manufacturer": "Samsung",
    "model": "Pocophone F1",
    "platform": "Android 10",
    "serial_number": "7655264412ab",
    "uid": "c53890d3-f9b7-4615-81a6-01ea3f0865f8",
    "user_id": 5995,
    "version": 180
  },
  {
    "build_number": 197,
    "dt_current_timestamp": 1772135281866199,
    "id": 2137,
    "manufacturer": "Apple",
    "model": "Redmi Note 8",
    "platform": "Android 10",
    "serial_number": "c11374bd3e2c",
    "uid": "c431d4fa-ec22-4703-b42e-3630a09439c6",
    "user_id": 9782,
    "version": 52
  },
  {
    "build_number": 139,
    "dt_current_timestamp": 1772135281866208,
    "id": 7355,
    "manufacturer": "Samsung",
    "model": "Galaxy S9",
    "platform": "Windows 10",
    "serial_number": "f100e2cbb36a",
    "uid": "167f93a9-df52-4345-b310-79ff931bdf3a",
    "user_id": 1709,
    "version": 178
  },
  {
    "build_number": 298,
    "dt_current_timestamp": 1772135281866216,
    "id": 7364,
    "manufacturer": "Motorola",
    "model": "Galaxy S9",
    "platform": "Android 11",
    "serial_number": "4824a0705cfa",
    "uid": "b23dcb80-2e49-4ac6-9b1f-bb2cfe603906",
    "user_id": 3633,
    "version": 477
  },
  {
    "build_number": 168,
    "dt_current_timestamp": 1772135281866223,
    "id": 5839,
    "manufacturer": "Xiaomi",
    "model": "Galaxy S9",
    "platform": "iOS 14",
    "serial_number": "f8008ce49dcc",
    "uid": "0d7f9d0c-e0dd-4005-9162-86d86939dc6b",
    "user_id": 8191,
    "version": 53
  }
]